zeta/__init__.py
zeta/models/BEiT3.py
zeta/models/LongNet.py
zeta/models/Magneto.py
zeta/models/__init__.py
zeta/models/andromeda.py
zeta/models/base.py
zeta/models/gpt4.py
zeta/models/kosmos.py
zeta/models/llama.py
zeta/models/max_vit.py
zeta/models/mega_vit.py
zeta/models/mm_mamba.py
zeta/models/navit.py
zeta/models/palme.py
zeta/models/vit.py
zeta/nn/__init__.py
zeta/nn/attention/__init__.py
zeta/nn/attention/agent_attn.py
zeta/nn/attention/attend.py
zeta/nn/attention/base.py
zeta/nn/attention/cross_attention.py
zeta/nn/attention/cross_attn_images.py
zeta/nn/attention/dilated_attention.py
zeta/nn/attention/flash_attention.py
zeta/nn/attention/linear_attention.py
zeta/nn/attention/linear_attn_l.py
zeta/nn/attention/linearized_attention.py
zeta/nn/attention/local_attention.py
zeta/nn/attention/local_attention_mha.py
zeta/nn/attention/mixture_attention.py
zeta/nn/attention/multi_grouped_attn.py
zeta/nn/attention/multi_modal_causal_attention.py
zeta/nn/attention/multi_modal_cross_attn.py
zeta/nn/attention/multihead_attention.py
zeta/nn/attention/multiquery_attention.py
zeta/nn/attention/scalable_img_self_attn.py
zeta/nn/attention/shaped_attention.py
zeta/nn/attention/sparse_attention.py
zeta/nn/attention/spatial_linear_attention.py
zeta/nn/attention/xc_attention.py
zeta/nn/biases/__init__.py
zeta/nn/biases/alibi.py
zeta/nn/biases/base.py
zeta/nn/biases/dynamic_position_bias.py
zeta/nn/biases/relative_position_bias.py
zeta/nn/embeddings/__init__.py
zeta/nn/embeddings/abc_pos_emb.py
zeta/nn/embeddings/base.py
zeta/nn/embeddings/embedding.py
zeta/nn/embeddings/mi_rope.py
zeta/nn/embeddings/multiway_network.py
zeta/nn/embeddings/nominal_embeddings.py
zeta/nn/embeddings/patch_embedding.py
zeta/nn/embeddings/pi.md
zeta/nn/embeddings/positional.py
zeta/nn/embeddings/positional_interpolation.py
zeta/nn/embeddings/qfsp_embeddings.py
zeta/nn/embeddings/qft_embeddings.py
zeta/nn/embeddings/rope.py
zeta/nn/embeddings/scaled_sinusoidal_embeddings.py
zetascale-2.8.8.dist-info/LICENSE
zetascale-2.8.8.dist-info/METADATA
zetascale-2.8.8.dist-info/WHEEL
zetascale-2.8.8.dist-info/RECORD
