Metadata-Version: 2.3
Name: zetascale
Version: 2.8.8
Summary: LEGO blocks for AI: Build state-of-the-art models faster with modular PyTorch components.
License: MIT
Keywords: artificial intelligence,deep learning,optimizers,Prompt Engineering,swarms,agents,llms,transformers,multi-agent,swarms of agents,Enterprise-Grade Agents,Production-Grade Agents,Agents,Multi-Grade-Agents,Swarms,Transformers,LLMs,Prompt Engineering,Agents,Generative Agents,Generative AI,Agent Marketplace,Agent Store,LSTMS,GRUs,RNNs,CNNs,MLPs,DNNs
Author: Zeta Team
Author-email: kye@apac.ai
Requires-Python: >=3.10,<4.0
Classifier: Development Status :: 4 - Beta
Classifier: Intended Audience :: Developers
Classifier: License :: OSI Approved :: MIT License
Classifier: Programming Language :: Python :: 3
Classifier: Programming Language :: Python :: 3.10
Classifier: Programming Language :: Python :: 3.11
Classifier: Programming Language :: Python :: 3.12
Classifier: Programming Language :: Python :: 3.13
Classifier: Topic :: Scientific/Engineering :: Artificial Intelligence
Requires-Dist: accelerate
Requires-Dist: argparse (>=1.4.0,<2.0.0)
Requires-Dist: beartype
Requires-Dist: bitsandbytes
Requires-Dist: colt5-attention
Requires-Dist: einops
Requires-Dist: einops-exts (==0.0.4)
Requires-Dist: joblib (>=1.3.0,<1.4.0)
Requires-Dist: local-attention
Requires-Dist: loguru
Requires-Dist: rich
Requires-Dist: scikit-learn (>=1.5.0,<1.6.0)
Requires-Dist: torch
Requires-Dist: torchvision
Requires-Dist: tqdm
Requires-Dist: transformers (>=4.20.0,<5.0.0)
Requires-Dist: vector-quantize-pytorch
Project-URL: Homepage, https://github.com/kyegomez/zeta
